ElasticsearchLibrary.py
robotframework_elasticsearchlibrary-2.0.0.dist-info/LICENSE
robotframework_elasticsearchlibrary-2.0.0.dist-info/METADATA
robotframework_elasticsearchlibrary-2.0.0.dist-info/WHEEL
robotframework_elasticsearchlibrary-2.0.0.dist-info/top_level.txt
robotframework_elasticsearchlibrary-2.0.0.dist-info/RECORD
