Metadata-Version: 2.1
Name: robotframework-elasticsearchlibrary
Version: 2.0.0
Summary: Robot Framework Elasticsearch Library.
Home-page: https://github.com/peterservice-rnd/robotframework-elasticsearchlibrary
Author: JSC PETER-SERVICE
Author-email: mf_aist_all@billing.ru
License: Apache License 2.0
Keywords: testing testautomation robotframework autotest elasticsearch
Platform: UNKNOWN
Classifier: Development Status :: 5 - Production/Stable
Classifier: Intended Audience :: Developers
Classifier: Topic :: Software Development :: Testing
Classifier: License :: OSI Approved :: Apache Software License
Classifier: Programming Language :: Python :: 3.5
Classifier: Programming Language :: Python :: 3.6
Classifier: Framework :: Robot Framework :: Library
Requires-Dist: elasticsearch (==2.4.0)
Requires-Dist: robotframework (==3.0.3)
